mircat_seg/__init__.py
mircat_seg/core.py
mircat_seg/models/__init__.py
mircat_seg-0.1.1.dist-info/METADATA
mircat_seg-0.1.1.dist-info/WHEEL
mircat_seg-0.1.1.dist-info/entry_points.txt
mircat_seg-0.1.1.dist-info/RECORD
