Metadata-Version: 2.3
Name: mircat-seg
Version: 0.1.1
Summary: Segmentation library for Mirshahi CT Analysis Toolkit (MirCAT).
Requires-Python: <3.12,>=3.10
Requires-Dist: dynamic-network-architectures>=0.3.1
Requires-Dist: monai==1.3.1
Requires-Dist: torch==2.3.1
